monadbox/__init__.py
MonadBox-0.0.1.dist-info/LICENSE
MonadBox-0.0.1.dist-info/METADATA
MonadBox-0.0.1.dist-info/WHEEL
MonadBox-0.0.1.dist-info/top_level.txt
MonadBox-0.0.1.dist-info/RECORD
